pipenv_freeze/__init__.py
pipenv_freeze/__main__.py
pipenv_freeze/cli.py
pipenv_freeze/freeze.py
pipenv_freeze-0.0.1.dist-info/LICENSE
pipenv_freeze-0.0.1.dist-info/METADATA
pipenv_freeze-0.0.1.dist-info/WHEEL
pipenv_freeze-0.0.1.dist-info/entry_points.txt
pipenv_freeze-0.0.1.dist-info/top_level.txt
pipenv_freeze-0.0.1.dist-info/RECORD
